torch_book-0.1.1.dist-info/METADATA
torch_book-0.1.1.dist-info/WHEEL
torch_book-0.1.1.dist-info/entry_points.txt
torch_book-0.1.1.dist-info/licenses/LICENSE
torch_book/__init__.py
torch_book/data/__init__.py
torch_book/data/cv/__init__.py
torch_book/data/cv/grid.py
torch_book/data/cv/plot.py
torch_book/data/cv/zipfile.py
torch_book/datasets/__init__.py
torch_book/datasets/cv/__init__.py
torch_book/datasets/cv/div2k.py
torch_book/metrics/__init__.py
torch_book/metrics/utils.py
torch_book/vision/__init__.py
torch_book/vision/classifier.py
torch_book/vision/utils.py
torch_book/web/__init__.py
torch_book/web/stream.py
torch_book-0.1.1.dist-info/RECORD
