Metadata-Version: 2.1
Name: torch-book
Version: 0.1.1
Summary: 道法自然
Author-Email: xinetzone <735613050@qq.com>
Maintainer-Email: xinetzone <735613050@qq.com>
License:                                  Apache License
Project-URL: Home, https://github.com/xinetzone/torch-book
Requires-Python: >=3.10
Provides-Extra: doc
Requires-Dist: xyzstyle; extra == "doc"
Requires-Dist: sphinx; extra == "doc"
Requires-Dist: ipywidgets; extra == "doc"
Requires-Dist: folium; extra == "doc"
Requires-Dist: numpy; extra == "doc"
Requires-Dist: matplotlib; extra == "doc"
Requires-Dist: sphinx-comments; extra == "doc"
Requires-Dist: myst-nb; extra == "doc"
Requires-Dist: nbclient; extra == "doc"
Requires-Dist: pandas; extra == "doc"
Requires-Dist: plotly; extra == "doc"
Requires-Dist: sphinx-design; extra == "doc"
Requires-Dist: sphinx-examples; extra == "doc"
Requires-Dist: sphinx-copybutton; extra == "doc"
Requires-Dist: sphinx-contributors; extra == "doc"
Requires-Dist: sphinx-thebe; extra == "doc"
Requires-Dist: sphinxcontrib-bibtex; extra == "doc"
Requires-Dist: sphinxext-opengraph; extra == "doc"
Requires-Dist: sphinx-sitemap; extra == "doc"
Requires-Dist: sphinx-autoapi>=3.4; extra == "doc"
Requires-Dist: graphviz; extra == "doc"
Requires-Dist: sphinxcontrib-mermaid; extra == "doc"
Requires-Dist: sphinx-proof; extra == "doc"
Requires-Dist: ultralytics; extra == "doc"
Provides-Extra: flows
Requires-Dist: taolib[flows]; extra == "flows"
Provides-Extra: gui
Requires-Dist: PySide6; extra == "gui"
